.gitignore
MANIFEST.in
README.rst
bootstrap.py
buildout.cfg
setup.py
docs/CONTRIBUTORS.rst
docs/GPL.txt
docs/HISTORY.rst
src/collective/__init__.py
src/collective.recipe.htpasswd.egg-info/PKG-INFO
src/collective.recipe.htpasswd.egg-info/SOURCES.txt
src/collective.recipe.htpasswd.egg-info/dependency_links.txt
src/collective.recipe.htpasswd.egg-info/entry_points.txt
src/collective.recipe.htpasswd.egg-info/namespace_packages.txt
src/collective.recipe.htpasswd.egg-info/not-zip-safe
src/collective.recipe.htpasswd.egg-info/requires.txt
src/collective.recipe.htpasswd.egg-info/top_level.txt
src/collective/recipe/__init__.py
src/collective/recipe/htpasswd/README.txt
src/collective/recipe/htpasswd/__init__.py
src/collective/recipe/htpasswd/tests/__init__.py
src/collective/recipe/htpasswd/tests/test_docs.py