Metadata-Version: 1.1
Name: collective.recipe.htpasswd
Version: 0.1a3
Summary: Buildout recipe for create and update the flat-files used to store usernames and password for basic authentication of HTTP users
Home-page: http://github.com/collective/collective.recipe.htpasswd
Author: Juan A. Diaz
Author-email: nueces@ravvit.net
License: GPL
Keywords: buildout,recipe,htpasswd,password,httpd,apache,nginx
Platform: UNKNOWN
Classifier: Framework :: Buildout
Classifier: Intended Audience :: Developers
Classifier: Topic :: Software Development :: Build Tools
Classifier: License :: OSI Approved :: GNU General Public License (GPL)
